phishfry/__init__.py
phishfry/account.py
phishfry/errors.py
phishfry/folder.py
phishfry/mailbox.py
phishfry/message.py
phishfry/namespaces.py
phishfry/remediation_result.py
phishfry/restriction.py
phishfry-1.0.1.dist-info/LICENSE
phishfry-1.0.1.dist-info/METADATA
phishfry-1.0.1.dist-info/WHEEL
phishfry-1.0.1.dist-info/top_level.txt
phishfry-1.0.1.dist-info/RECORD
