Metadata-Version: 2.1
Name: phishfry
Version: 1.0.1
Summary: Python library and command line tool for removing/restoring emails in office365/Exchange using EWS API
Home-page: https://github.com/ace-ecosystem/phishfry
Author: Cole Robinette
Author-email: robinette.31@gmail.com
License: UNKNOWN
Keywords: ews exchange microsoft outlook exchange-web-services o365 office365
Platform: UNKNOWN
Requires-Python: >=2.7
Requires-Dist: requests (>=2.7)
Requires-Dist: lxml (>3.0)
Requires-Dist: requests-ntlm
